jmf_custom_pf_tools/__init__.py
jmf_custom_pf_tools/tools/__init__.py
jmf_custom_pf_tools/tools/apim_openai_tool.py
jmf_custom_pf_tools/tools/get_token_tool.py
jmf_custom_pf_tools/tools/openai_llm_tool.py
jmf_custom_pf_tools/tools/utils.py
jmf_custom_pf_tools/yamls/apim_openai_tool.yaml
jmf_custom_pf_tools/yamls/get_token_tool.yaml
jmf_custom_pf_tools/yamls/openai_llm_tool.yaml
jmf_custom_pf_tools-0.0.1.dist-info/METADATA
jmf_custom_pf_tools-0.0.1.dist-info/WHEEL
jmf_custom_pf_tools-0.0.1.dist-info/entry_points.txt
jmf_custom_pf_tools-0.0.1.dist-info/top_level.txt
jmf_custom_pf_tools-0.0.1.dist-info/RECORD
