Metadata-Version: 2.1
Name: jmf-custom-pf-tools
Version: 0.0.1
Summary: This is my tools package
